Workbook

Sheet Daily_Sales
A1: STEP 1 — UPDATE: Daily units sold (scheduled export first; approved connector later)
A2: ILLUSTRATIVE 28-day history. Case-based product speeds are used as the baseline; this is not live PopCart data.
A3: Date | B3: Freeze-Dried Candy Mix | C3: Spicy Korean Ramen Bundles | D3: Giant Bubble Gum Tubs | E3: Assorted Chocolate Crunch Bars | F3: Sour Belts & Bulk Packs
A4: May 25 | B4: 310 | C4: 260 | D4: 166 | E4: 156 | F4: 120
A5: May 26 | B5: 266 | C5: 246 | D5: 190 | E5: 149 | F5: 111
A6: May 27 | B6: 284 | C6: 258 | D6: 165 | E6: 179 | F6: 132
A7: May 28 | B7: 280 | C7: 253 | D7: 175 | E7: 160 | F7: 131
A8: May 29 | B8: 317 | C8: 242 | D8: 201 | E8: 144 | F8: 114
A9: May 30 | B9: 313 | C9: 267 | D9: 186 | E9: 143 | F9: 124
A10: May 31 | B10: 328 | C10: 233 | D10: 182 | E10: 145 | F10: 123
A11: Jun 01 | B11: 270 | C11: 243 | D11: 188 | E11: 165 | F11: 110
A12: Jun 02 | B12: 294 | C12: 259 | D12: 195 | E12: 171 | F12: 128
A13: Jun 03 | B13: 266 | C13: 247 | D13: 192 | E13: 157 | F13: 121
A14: Jun 04 | B14: 280 | C14: 261 | D14: 168 | E14: 143 | F14: 128
A15: Jun 05 | B15: 300 | C15: 244 | D15: 160 | E15: 155 | F15: 121
... A31: Jun 21 (today) | B31: 366 | C31: 246 | D31: 158 | E31: 169 | F31: 109

Sheet Control_Panel
A1: STEP 2 — REORDER CONTROL PANEL · "the fuel light for every SKU"
A2: Reorder Point = forecast daily demand × lead time + safety stock. Status flags 🔴 when stock on hand falls to/below it. System recommends; founder decides.
A3: SKU | B3: Price ₱ | C3: Lead (days) | D3: Stock on hand | E3: Avg/day (7d) | F3: Avg/day (14d) | G3: Avg/day (28d) | H3: TikTok idx (0-100) | I3: Viral × | J3: Forecast /day | K3: Safety stock | L3: Reorder point | M3: STATUS | N3: Suggested order qty | O3: Days cover | P3: ₱ contribution if OOS/day
A4: Freeze-Dried Candy Mix | B4: 180 | C4: 14 | D4: 2500 | E4: =ROUND(AVERAGE(Daily_Sales!B25:B31),0) | F4: =ROUND(AVERAGE(Daily_Sales!B18:B31),0) | G4: =ROUND(AVERAGE(Daily_Sales!B4:B31),0) | H4: 88 | I4: =1+MIN(0.4,MAX(0,(H4-60)/100)) | J4: =ROUND((0.5*E4+0.3*F4+0.2*G4)*I4,0) | K4: =ROUND(1.65*STDEV(Daily_Sales!B4:B31)*SQRT(C4),0) | L4: =ROUND(J4*C4+K4,0) | M4: =IF(D4<=L4,"🔴 REORDER NOW","🟢 OK") | N4: =IF(D4<=L4,ROUNDUP(J4*(C4+14)+K4-D4,0),0) | O4: =ROUND(D4/J4,1) | P4: =ROUND(J4*B4*0.3,0)
A5: Spicy Korean Ramen Bundles | B5: 320 | C5: 30 | D5: 5000 | E5: =ROUND(AVERAGE(Daily_Sales!C25:C31),0) | F5: =ROUND(AVERAGE(Daily_Sales!C18:C31),0) | G5: =ROUND(AVERAGE(Daily_Sales!C4:C31),0) | H5: 64 | I5: =1+MIN(0.4,MAX(0,(H5-60)/100)) | J5: =ROUND((0.5*E5+0.3*F5+0.2*G5)*I5,0) | K5: =ROUND(1.65*STDEV(Daily_Sales!C4:C31)*SQRT(C5),0) | L5: =ROUND(J5*C5+K5,0) | M5: =IF(D5<=L5,"🔴 REORDER NOW","🟢 OK") | N5: =IF(D5<=L5,ROUNDUP(J5*(C5+14)+K5-D5,0),0) | O5: =ROUND(D5/J5,1) | P5: =ROUND(J5*B5*0.3,0)
A6: Giant Bubble Gum Tubs | B6: 220 | C6: 7 | D6: 3200 | E6: =ROUND(AVERAGE(Daily_Sales!D25:D31),0) | F6: =ROUND(AVERAGE(Daily_Sales!D18:D31),0) | G6: =ROUND(AVERAGE(Daily_Sales!D4:D31),0) | H6: 45 | I6: =1+MIN(0.4,MAX(0,(H6-60)/100)) | J6: =ROUND((0.5*E6+0.3*F6+0.2*G6)*I6,0) | K6: =ROUND(1.65*STDEV(Daily_Sales!D4:D31)*SQRT(C6),0) | L6: =ROUND(J6*C6+K6,0) | M6: =IF(D6<=L6,"🔴 REORDER NOW","🟢 OK") | N6: =IF(D6<=L6,ROUNDUP(J6*(C6+14)+K6-D6,0),0) | O6: =ROUND(D6/J6,1) | P6: =ROUND(J6*B6*0.3,0)
A7: Assorted Chocolate Crunch Bars | B7: 150 | C7: 21 | D7: 3000 | E7: =ROUND(AVERAGE(Daily_Sales!E25:E31),0) | F7: =ROUND(AVERAGE(Daily_Sales!E18:E31),0) | G7: =ROUND(AVERAGE(Daily_Sales!E4:E31),0) | H7: 70 | I7: =1+MIN(0.4,MAX(0,(H7-60)/100)) | J7: =ROUND((0.5*E7+0.3*F7+0.2*G7)*I7,0) | K7: =ROUND(1.65*STDEV(Daily_Sales!E4:E31)*SQRT(C7),0) | L7: =ROUND(J7*C7+K7,0) | M7: =IF(D7<=L7,"🔴 REORDER NOW","🟢 OK") | N7: =IF(D7<=L7,ROUNDUP(J7*(C7+14)+K7-D7,0),0) | O7: =ROUND(D7/J7,1) | P7: =ROUND(J7*B7*0.3,0)
A8: Sour Belts & Bulk Packs | B8: 120 | C8: 7 | D8: 2600 | E8: =ROUND(AVERAGE(Daily_Sales!F25:F31),0) | F8: =ROUND(AVERAGE(Daily_Sales!F18:F31),0) | G8: =ROUND(AVERAGE(Daily_Sales!F4:F31),0) | H8: 50 | I8: =1+MIN(0.4,MAX(0,(H8-60)/100)) | J8: =ROUND((0.5*E8+0.3*F8+0.2*G8)*I8,0) | K8: =ROUND(1.65*STDEV(Daily_Sales!F4:F31)*SQRT(C8),0) | L8: =ROUND(J8*C8+K8,0) | M8: =IF(D8<=L8,"🔴 REORDER NOW","🟢 OK") | N8: =IF(D8<=L8,ROUNDUP(J8*(C8+14)+K8-D8,0),0) | O8: =ROUND(D8/J8,1) | P8: =ROUND(J8*B8*0.3,0)
A11: How to read this panel:
A12: • Forecast/day = weighted recency (50% of 7-day, 30% of 14-day, 20% of 28-day) × viral multiplier.
A13: • Viral × rises with the TikTok engagement index (leading signal) — pre-empts a spike before sales fully show it.
A14: • Safety stock = 1.65 × demand volatility (st-dev) × √lead time → ~95% service level; bigger when sales are choppy or lead times long.
A15: • Reorder point (the fuel light) = forecast/day × lead time + safety stock. Order BEFORE stock hits it, because restock takes the lead time to arrive.
A16: • ₱ contribution if OOS/day = forecast/day × price × 30% — an illustrative exposure if the item becomes unavailable, not a claim of today's actual loss.

Sheet Dashboard
A1: PopCart — Morning Control Dashboard
A2: Prototype using case baselines + illustrative operating data. All figures live-linked to the Control Panel.
A4: SKUs to reorder TODAY | C4: ₱ contribution exposed if OOS/day | E4: Viral items rising 🔥
A5: =COUNTIF(Control_Panel!M4:M8,"*REORDER*") | C5: =SUMIF(Control_Panel!M4:M8,"*REORDER*",Control_Panel!P4:P8) | E5: =COUNTIF(Control_Panel!I4:I8,">1.1")
A8: TODAY'S ACTION LIST (system recommends — founder approves)
A9: SKU | B9: Status | C9: Suggested order qty | D9: Days cover left | E9: ₱ if OOS/day | F9: Trend
A10: =Control_Panel!A4 | B10: =Control_Panel!M4 | C10: =Control_Panel!N4 | D10: =Control_Panel!O4 | E10: =Control_Panel!P4 | F10: =IF(Control_Panel!I4>1.1,"🔥 rising","steady")
A11: =Control_Panel!A5 | B11: =Control_Panel!M5 | C11: =Control_Panel!N5 | D11: =Control_Panel!O5 | E11: =Control_Panel!P5 | F11: =IF(Control_Panel!I5>1.1,"🔥 rising","steady")
A12: =Control_Panel!A6 | B12: =Control_Panel!M6 | C12: =Control_Panel!N6 | D12: =Control_Panel!O6 | E12: =Control_Panel!P6 | F12: =IF(Control_Panel!I6>1.1,"🔥 rising","steady")
A13: =Control_Panel!A7 | B13: =Control_Panel!M7 | C13: =Control_Panel!N7 | D13: =Control_Panel!O7 | E13: =Control_Panel!P7 | F13: =IF(Control_Panel!I7>1.1,"🔥 rising","steady")
A14: =Control_Panel!A8 | B14: =Control_Panel!M8 | C14: =Control_Panel!N8 | D14: =Control_Panel!O8 | E14: =Control_Panel!P8 | F14: =IF(Control_Panel!I8>1.1,"🔥 rising","steady")
A16: "Reorder before the shelf is empty — not after. The fuel light, for snacks."

Sheet README
A1: PopCart PH — Forecasting & Reorder Control System (prototype)
A2: Built for LAMBO 2026, Slide 9. A working demo of the proposed decision process — not PopCart's finished or live system.
A4: THE 5-STEP WORKFLOW
A5: 1. UPDATE — Start with scheduled exports into Excel/Power Query, 2–3×/day. Use an approved connector later if PopCart chooses.
A6: Replaces the manual twice-a-day Excel — like switching from checking your bank balance twice a day to online banking.
A7: 2. COMPARE — estimate recent demand, then compare days of stock with supplier delivery time.
A8: 3. WARN — flag products that may run out before the next delivery can arrive.
A9: 4. DECIDE — founder checks cash, supplier availability, and minimum order size before approving.
A10: 5. LEARN — compare alerts with actual results weekly; add trend signals only after the basic data is reliable.
A12: WHY IT FIXES THE PHP 7.35M LEAK
A13: Today PopCart reorders on gut feel and only sees empty shelves AFTER they happen — fatal when restock takes 14–30 days.
A14: The reorder point is the low-fuel light: it warns with enough road left to refill before the tank hits empty.
... A24: This prototype's formulas + sample data were drafted with AI assistance and verified by the team against the case exhibits.
